strideutils/Makefile
strideutils/__init__.py
strideutils/__init__.pyi
strideutils/coingecko.py
strideutils/coingecko.pyi
strideutils/cryptography.py
strideutils/cryptography.pyi
strideutils/exec_tx.py
strideutils/exec_tx.pyi
strideutils/py.typed
strideutils/redis_connector.py
strideutils/redis_connector.pyi
strideutils/run_safely.py
strideutils/run_safely.pyi
strideutils/sheets_connector.py
strideutils/sheets_connector.pyi
strideutils/slack_connector.py
strideutils/slack_connector.pyi
strideutils/stride_alerts.py
strideutils/stride_alerts.pyi
strideutils/stride_config.py
strideutils/stride_config.pyi
strideutils/stride_requests.py
strideutils/stride_requests.pyi
strideutils/telegram_connector.py
strideutils/telegram_connector.pyi
strideutils/twilio_connector.py
strideutils/twilio_connector.pyi
strideutils/types.py
strideutils/types.pyi
strideutils/config_examples/env.local.example
strideutils/config_examples/strideutils_config.yaml.example
strideutils-0.8.23.dist-info/licenses/LICENSE
strideutils-stubs/__init__.pyi
strideutils-stubs/coingecko.pyi
strideutils-stubs/cryptography.pyi
strideutils-stubs/exec_tx.pyi
strideutils-stubs/redis_connector.pyi
strideutils-stubs/run_safely.pyi
strideutils-stubs/sheets_connector.pyi
strideutils-stubs/slack_connector.pyi
strideutils-stubs/stride_alerts.pyi
strideutils-stubs/stride_config.pyi
strideutils-stubs/stride_requests.pyi
strideutils-stubs/telegram_connector.pyi
strideutils-stubs/twilio_connector.pyi
strideutils-stubs/types.pyi
strideutils-0.8.23.dist-info/METADATA
strideutils-0.8.23.dist-info/WHEEL
strideutils-0.8.23.dist-info/top_level.txt
strideutils-0.8.23.dist-info/RECORD
