Metadata-Version: 2.4
Name: strideutils
Version: 0.8.23
Summary: Utility functions for monitoring the Stride blockchain
Author-email: Stride Labs <hello@stridelabs.co>
License: MIT License
Classifier: Programming Language :: Python :: 3
Requires-Python: >=3.11
License-File: LICENSE
Requires-Dist: python-telegram-bot==22.0
Requires-Dist: google-api-python-client>=2.149.0
Requires-Dist: google-auth-httplib2>=0.2.0
Requires-Dist: google-auth-oauthlib>=1.2.1
Requires-Dist: google-cloud-bigquery>=3.26.0
Requires-Dist: gspread>=6.1.3
Requires-Dist: pytz>=2023.3
Requires-Dist: redis>=4.5.4
Requires-Dist: bech32>=1.2.0
Requires-Dist: slack-sdk>=3.23.0
Requires-Dist: pandas>=2.1.1
Requires-Dist: twilio>=8.10.0
Requires-Dist: tabulate>=0.9.0
Requires-Dist: python-dotenv==1.0.1
Requires-Dist: pyyaml>=6.0.1
Requires-Dist: requests>=2.32.3
Requires-Dist: pycryptodome>=3.20.0
Requires-Dist: web3==7.6.1
Provides-Extra: dev
Requires-Dist: pytest>=8.1.1; extra == "dev"
Requires-Dist: mypy>=1.10.0; extra == "dev"
Requires-Dist: flake8>=7.0.0; extra == "dev"
Requires-Dist: black>=24.4.1; extra == "dev"
Requires-Dist: types-pyyaml>=6.0.12.20240917; extra == "dev"
Requires-Dist: twilio-stubs>=0.2.0; extra == "dev"
Requires-Dist: pandas-stubs>=2.2.1.240316; extra == "dev"
Requires-Dist: types-tabulate>=0.9.0.20240106; extra == "dev"
Requires-Dist: types-requests>=2.31.0.20240406; extra == "dev"
Requires-Dist: isort>=5.13.2; extra == "dev"
Provides-Extra: build
Requires-Dist: build>=1.2.2.post1; extra == "build"
Requires-Dist: bump2version>=1.0.1; extra == "build"
Requires-Dist: setuptools>=75.1.0; extra == "build"
Requires-Dist: toml-cli>=0.7.0; extra == "build"
Requires-Dist: twine>=5.1.1; extra == "build"
Requires-Dist: wheel>=0.44.0; extra == "build"
Dynamic: license-file
